introduce/__init__.py
introduce/introduce.py
introduce-0.0.7.dist-info/METADATA
introduce-0.0.7.dist-info/WHEEL
introduce-0.0.7.dist-info/top_level.txt
introduce-0.0.7.dist-info/RECORD
