Metadata-Version: 2.1
Name: introduce
Version: 0.0.7
Summary: 자기소개 라이브러리
Home-page: https://github.com/cord0318/python_introduce
Author: Jung Ji-Hyo
Author-email: cord0318@gmail.com
License: GPL-V3
Keywords: korea,auto,pillow,introduce,introduction
Platform: UNKNOWN
Classifier: Programming Language :: Python :: 3.8
Classifier: License :: OSI Approved :: GNU General Public License v3 (GPLv3)
Classifier: Development Status :: 5 - Production/Stable
Requires-Python: >=3
Requires-Dist: pillow
